Metadata-Version: 2.1
Name: opigpiogalluss
Version: 0.8
Summary: opigpiogalluss
Author: Gallus
Author-email: bkmz_repvby@mail.ru
